tensorguard/__init__.py
tensorguard/dim_specs.py
tensorguard/exception.py
tensorguard/guard.py
tensorguard/parser.py
tensorguard/shape_spec.py
tensorguard/shape_spec_parser.py
tensorguard/tools.py
tensorguard-1.0.2.dist-info/licenses/LICENSE
tensorguard-1.0.2.dist-info/METADATA
tensorguard-1.0.2.dist-info/WHEEL
tensorguard-1.0.2.dist-info/top_level.txt
tensorguard-1.0.2.dist-info/RECORD
